alvenir_grpc_contracts/__init__.py
alvenir_grpc_contracts/asr/__init__.py
alvenir_grpc_contracts/asr/v1/__init__.py
alvenir_grpc_contracts/asr/v1/asr_pb2.py
alvenir_grpc_contracts/asr/v1/asr_pb2.pyi
alvenir_grpc_contracts/asr/v1/asr_pb2_grpc.py
alvenir_grpc_contracts/assistance/__init__.py
alvenir_grpc_contracts/assistance/v1/__init__.py
alvenir_grpc_contracts/assistance/v1/assistance_pb2.py
alvenir_grpc_contracts/assistance/v1/assistance_pb2.pyi
alvenir_grpc_contracts/assistance/v1/assistance_pb2_grpc.py
alvenir_grpc_contracts/guidance/__init__.py
alvenir_grpc_contracts/guidance/v1/__init__.py
alvenir_grpc_contracts/guidance/v1/guidance_pb2.py
alvenir_grpc_contracts/guidance/v1/guidance_pb2.pyi
alvenir_grpc_contracts/guidance/v1/guidance_pb2_grpc.py
alvenir_grpc_contracts/summary/__init__.py
alvenir_grpc_contracts/summary/v1/__init__.py
alvenir_grpc_contracts/summary/v1/analytics_pb2.py
alvenir_grpc_contracts/summary/v1/analytics_pb2.pyi
alvenir_grpc_contracts/summary/v1/analytics_pb2_grpc.py
alvenir_grpc_contracts/summary/v1/summary_pb2.py
alvenir_grpc_contracts/summary/v1/summary_pb2.pyi
alvenir_grpc_contracts/summary/v1/summary_pb2_grpc.py
alvenir_grpc_contracts/types/__init__.py
alvenir_grpc_contracts/types/v1/__init__.py
alvenir_grpc_contracts/types/v1/format_pb2.py
alvenir_grpc_contracts/types/v1/format_pb2.pyi
alvenir_grpc_contracts/types/v1/format_pb2_grpc.py
alvenir_grpc_contracts/types/v1/ping_pb2.py
alvenir_grpc_contracts/types/v1/ping_pb2.pyi
alvenir_grpc_contracts/types/v1/ping_pb2_grpc.py
alvenir_grpc_contracts/types/v1/status_pb2.py
alvenir_grpc_contracts/types/v1/status_pb2.pyi
alvenir_grpc_contracts/types/v1/status_pb2_grpc.py
alvenir_grpc_contracts-0.0.2.dist-info/METADATA
alvenir_grpc_contracts-0.0.2.dist-info/WHEEL
alvenir_grpc_contracts-0.0.2.dist-info/RECORD
