Metadata-Version: 2.4
Name: alvenir_grpc_contracts
Version: 0.0.2
Summary: Generated gRPC python files for interacting with Alvenir Services
Project-URL: Homepage, https://github.com/alvenirai/alvenir-grpc-contracts
Project-URL: Issues, https://github.com/alvenirai/alvenir-grpc-contracts/issues
Author-email: Moesen <gustav@alvenir.ai>
Classifier: Operating System :: OS Independent
Classifier: Programming Language :: Python :: 3
Requires-Python: >=3.10
Requires-Dist: grpcio>=1.59.0
Requires-Dist: protobuf>=5.29.3
Provides-Extra: dev
Requires-Dist: grpcio-tools>=1.59.0; extra == 'dev'
